MANIFEST.in
README.md
setup.py
multitool_cal_view/__init__.py
multitool_cal_view.egg-info/PKG-INFO
multitool_cal_view.egg-info/SOURCES.txt
multitool_cal_view.egg-info/dependency_links.txt
multitool_cal_view.egg-info/top_level.txt
multitool_cal_view/templates/calendar/calendar.html
multitool_cal_view/templates/calendar/reservation_event_feed.html