Metadata-Version: 2.1
Name: multitool-cal-view
Version: 0.0.1
Summary: NEMO Plugin - Multi-Tool Calendar View
Home-page: UNKNOWN
License: UNKNOWN
Platform: UNKNOWN
